pysimenv/__init__.py
pysimenv/common/__init__.py
pysimenv/common/model.py
pysimenv/common/orientation.py
pysimenv/common/util.py
pysimenv/core/__init__.py
pysimenv/core/base.py
pysimenv/core/error.py
pysimenv/core/simulator.py
pysimenv/core/util.py
pysimenv-0.0.22.dist-info/METADATA
pysimenv-0.0.22.dist-info/WHEEL
pysimenv-0.0.22.dist-info/top_level.txt
pysimenv-0.0.22.dist-info/RECORD
